datasette_edit_tables/__init__.py
datasette_edit_tables/templates/edit_tables_database.html
datasette_edit_tables/templates/edit_tables_index.html
datasette_edit_tables/templates/edit_tables_table.html
datasette_edit_tables-0.3a1.dist-info/LICENSE
datasette_edit_tables-0.3a1.dist-info/METADATA
datasette_edit_tables-0.3a1.dist-info/WHEEL
datasette_edit_tables-0.3a1.dist-info/entry_points.txt
datasette_edit_tables-0.3a1.dist-info/top_level.txt
datasette_edit_tables-0.3a1.dist-info/RECORD
