Metadata-Version: 2.1
Name: datasette-edit-tables
Version: 0.3a1
Summary: Datasette plugin for renaming and deleting tables and columns and changing column types
Home-page: https://github.com/simonw/datasette-edit-tables
Author: Simon Willison
License: Apache License, Version 2.0
Platform: UNKNOWN
Requires-Dist: datasette (>=0.44)
Requires-Dist: sqlite-utils (>=2.21)
Provides-Extra: test
Requires-Dist: pytest ; extra == 'test'
Requires-Dist: pytest-asyncio ; extra == 'test'
Requires-Dist: httpx ; extra == 'test'
